{"cameraMode":{"drawMode":0,"name":"Shaded","section":"Shading Mode"},"sceneLighting":false,"audioPlay":false,"sceneViewState":{"showFog":true,"showMaterialUpdate":false,"showSkybox":false,"showFlares":true,"showImageEffects":true,"showParticleSystems":true},"in2DMode":false,"pivot":{"x":2.4674460887908937,"y":2.4799695014953615,"z":7.246752738952637},"rotation":{"x":-0.257922887802124,"y":0.08449714630842209,"z":-0.022653989493846895,"w":-0.9622037410736084},"size":1.4045639038085938,"orthographic":false}